spt3g/__init__.py
spt3g/_libcalibration.cpython-312-aarch64-linux-gnu.so
spt3g/_libcore.cpython-312-aarch64-linux-gnu.so
spt3g/_libdfmux.cpython-312-aarch64-linux-gnu.so
spt3g/_libgcp.cpython-312-aarch64-linux-gnu.so
spt3g/_libmaps.cpython-312-aarch64-linux-gnu.so
spt3g/version.py
spt3g/calibration/__init__.py
spt3g/calibration/bolopropertiesutils.py
spt3g/calibration/build_cal_frames.py
spt3g/core/__init__.py
spt3g/core/apidoc.py
spt3g/core/fileio.py
spt3g/core/g3decorators.py
spt3g/core/g3logging.py
spt3g/core/modconstruct.py
spt3g/core/multiprocess.py
spt3g/core/parse_pipeline_graph.py
spt3g/core/quatextensions.py
spt3g/core/timestreamextensions.py
spt3g/core/util.py
spt3g/dfmux/DataQualityTools.py
spt3g/dfmux/HardwareMapTools.py
spt3g/dfmux/Housekeeping.py
spt3g/dfmux/IceboardConversions.py
spt3g/dfmux/LegacyHousekeeping.py
spt3g/dfmux/ScanTools.py
spt3g/dfmux/TFPolyJSON_Rev3_Mezz.txt
spt3g/dfmux/TFPoly_full_with_10MHz_pi.txt
spt3g/dfmux/TuberClient.py
spt3g/dfmux/__init__.py
spt3g/dfmux/spt3g_filtering_2017_full.txt
spt3g/dfmux/unittransforms.py
spt3g/dfmux/wtl_ConvertUtils.py
spt3g/gcp/ARCExtractor.py
spt3g/gcp/ARCFile.py
spt3g/gcp/ARCHKExtractor.py
spt3g/gcp/CalFile.py
spt3g/gcp/G3RegCal.txt
spt3g/gcp/GCPDataTee.py
spt3g/gcp/InfluxDB.py
spt3g/gcp/__init__.py
spt3g/maps/__init__.py
spt3g/maps/azel.py
spt3g/maps/coordsysmodules.py
spt3g/maps/finals2000A.all
spt3g/maps/fitsio.py
spt3g/maps/map_modules.py
spt3g/maps/maputils.py
spt3g/maps/quathelpers.py
spt3g/maps/skymapaddons.py
spt3g/mpi/MPIAccumulator.py
spt3g/mpi/MPIFileIO.py
spt3g/mpi/README.rst
spt3g/mpi/TOASTFiller.py
spt3g/mpi/__init__.py
spt3g-1.0.1.data/scripts/gen-analysis-doc
spt3g-1.0.1.data/scripts/ledgerman
spt3g-1.0.1.data/scripts/spt3g-arc-dump
spt3g-1.0.1.data/scripts/spt3g-arc-verify
spt3g-1.0.1.data/scripts/spt3g-coadd-maps
spt3g-1.0.1.data/scripts/spt3g-dump
spt3g-1.0.1.data/scripts/spt3g-inspect
spt3g-1.0.1.dist-info/METADATA
spt3g-1.0.1.dist-info/WHEEL
spt3g-1.0.1.dist-info/top_level.txt
spt3g-1.0.1.dist-info/RECORD
spt3g-1.0.1.dist-info/licenses/LICENSE
