Metadata-Version: 2.4
Name: spt3g
Version: 1.0.1
Summary: Public Subset of Analysis Software Developed by the SPT-3G Collaboration
License-Expression: BSD-2-Clause
Project-URL: source, https://github.com/CMB-S4/spt3g_software
Requires-Python: >=3.7
License-File: LICENSE
Requires-Dist: numpy
Requires-Dist: scipy
Requires-Dist: astropy
Provides-Extra: dev
Requires-Dist: cmake; extra == "dev"
Requires-Dist: pytest; extra == "dev"
Requires-Dist: healpy; extra == "dev"
Dynamic: license-file
